veritascribe/__init__.py
veritascribe/__main__.py
veritascribe/config.py
veritascribe/data_models.py
veritascribe/llm_modules.py
veritascribe/main.py
veritascribe/pdf_processor.py
veritascribe/pipeline.py
veritascribe/py.typed
veritascribe/rate_limiter.py
veritascribe/report_generator.py
veritascribe/training_data.py
veritascribe-0.2.3.dist-info/METADATA
veritascribe-0.2.3.dist-info/WHEEL
veritascribe-0.2.3.dist-info/entry_points.txt
veritascribe-0.2.3.dist-info/licenses/LICENSE
veritascribe-0.2.3.dist-info/RECORD
