Metadata-Version: 2.4
Name: veritascribe
Version: 0.2.3
Summary: AI-powered bachelor thesis review tool for automated quality analysis
Project-URL: documentation, https://legout.github.io/veritascribe
Project-URL: homepage, https://github.com/legout/veritascribe
Author-email: legout <ligno.blades@gmail.com>
License-Expression: MIT
License-File: LICENSE
Requires-Python: >=3.13
Requires-Dist: dspy>=2.6.27
Requires-Dist: langdetect>=1.0.9
Requires-Dist: matplotlib>=3.10.5
Requires-Dist: openai>=1.98.0
Requires-Dist: pydantic-settings>=2.10.1
Requires-Dist: pydantic>=2.11.7
Requires-Dist: pymupdf>=1.26.3
Requires-Dist: pytest>=8.4.1
Requires-Dist: python-dotenv>=1.1.1
Requires-Dist: rich>=13.0.0
Requires-Dist: typer>=0.16.0
Provides-Extra: fasthtml
Requires-Dist: pandas>=2.3.1; extra == 'fasthtml'
Requires-Dist: plotly>=6.2.0; extra == 'fasthtml'
Requires-Dist: python-fasthtml>=0.12.23; extra == 'fasthtml'
Provides-Extra: panel
Requires-Dist: altair>=5.5.0; extra == 'panel'
Requires-Dist: duckdb>=1.3.2; extra == 'panel'
Requires-Dist: nbformat>=5.10.4; extra == 'panel'
Requires-Dist: pandas>=2.3.1; extra == 'panel'
Requires-Dist: panel-material-ui>=0.4.0; extra == 'panel'
Requires-Dist: panel>=1.7.5; extra == 'panel'
Requires-Dist: plotly>=6.2.0; extra == 'panel'
Requires-Dist: polars[pyarrow]>=1.32.0; extra == 'panel'
Requires-Dist: python-lsp-ruff>=2.2.2; extra == 'panel'
Requires-Dist: python-lsp-server>=1.13.0; extra == 'panel'
Requires-Dist: ruff>=0.12.7; extra == 'panel'
Requires-Dist: sqlglot>=27.6.0; extra == 'panel'
Requires-Dist: vegafusion>=2.0.2; extra == 'panel'
Requires-Dist: vl-convert-python>=1.8.0; extra == 'panel'
Requires-Dist: websockets>=15.0.1; extra == 'panel'
